Workbook

Sheet Account_Summary
A1: Metric | B1: Value | C1: Notes / Source
A2: Total Portfolio Value | B2: =Holdings!I24 | C2: Sum of active holdings market value (HKD)
A3: Available Cash Balance | B3: =Transactions!H2-Holdings!G24 | C3: Funded capital minus active cost basis
A4: Total Stock Market Value | B4: =Holdings!I24 | C4: Market value at Yahoo Finance screenshot prices
A5: Active Invested Cost Basis | B5: =Holdings!G24 | C5: Total cost basis across 78 imported share lots
A6: Unrealized P&L ($) | B6: =Holdings!J24 | C6: Total floating gain/loss across 22 active holdings
A7: Unrealized P&L (%) | B7: =IF(Holdings!G24>0, Holdings!J24/Holdings!G24, 0) | C7: Portfolio unrealized return percentage
A8: Realized P&L ($) | B8: 0 | C8: No closed sell trades in screenshots
A9: Total Dividends Earned ($) | B9: 0 | C9: No dividend logs in Share Lots view
A10: Active Positions Count | B10: =COUNTA(Holdings!A2:A23) | C10: 16 HK Equities + 6 HK ETFs extracted from 5 photos
A11: Imported Share Lots Count | B11: =COUNTA(Transactions!A3:A80) | C11: 78 BUY share lots + 1 funding deposit row

Sheet Holdings
A1: Ticker | B1: Company Name | C1: Sector | D1: Currency | E1: Shares Held | F1: Avg Cost Basis ($) | G1: Total Cost Basis ($) | H1: Current Price ($) | I1: Market Value ($) | J1: Unrealized P&L ($) | K1: Unrealized P&L (%) | L1: Yield on Cost (%) | M1: Total Dividends ($)
A2: 2318.HK | B2: Ping An Insurance (Group) Co of China Ltd | C2: Financials | D2: HKD | E2: =SUMIFS(Transactions!$E$3:$E$80, Transactions!$D$3:$D$80, A2, Transactions!$C$3:$C$80, "BUY") | F2: =IF(E2>0, G2/E2, 0) | G2: =SUMIFS(Transactions!$H$3:$H$80, Transactions!$D$3:$D$80, A2, Transactions!$C$3:$C$80, "BUY") | H2: 50.05 | I2: =ROUND(E2*H2, 2) | J2: =I2-G2 | K2: =IF(G2>0, (J2/G2)*100, 0) | L2: =IF(G2>0, (M2/G2)*100, 0) | M2: 0
A3: 0857.HK | B3: PetroChina Co Ltd | C3: Energy | D3: HKD | E3: =SUMIFS(Transactions!$E$3:$E$80, Transactions!$D$3:$D$80, A3, Transactions!$C$3:$C$80, "BUY") | F3: =IF(E3>0, G3/E3, 0) | G3: =SUMIFS(Transactions!$H$3:$H$80, Transactions!$D$3:$D$80, A3, Transactions!$C$3:$C$80, "BUY") | H3: 9.995 | I3: =ROUND(E3*H3, 2) | J3: =I3-G3 | K3: =IF(G3>0, (J3/G3)*100, 0) | L3: =IF(G3>0, (M3/G3)*100, 0) | M3: 0
A4: 0386.HK | B4: China Petroleum & Chemical Corp (Sinopec) | C4: Energy | D4: HKD | E4: =SUMIFS(Transactions!$E$3:$E$80, Transactions!$D$3:$D$80, A4, Transactions!$C$3:$C$80, "BUY") | F4: =IF(E4>0, G4/E4, 0) | G4: =SUMIFS(Transactions!$H$3:$H$80, Transactions!$D$3:$D$80, A4, Transactions!$C$3:$C$80, "BUY") | H4: 4.5 | I4: =ROUND(E4*H4, 2) | J4: =I4-G4 | K4: =IF(G4>0, (J4/G4)*100, 0) | L4: =IF(G4>0, (M4/G4)*100, 0) | M4: 0
A5: 0002.HK | B5: CLP Holdings Ltd | C5: Utilities | D5: HKD | E5: =SUMIFS(Transactions!$E$3:$E$80, Transactions!$D$3:$D$80, A5, Transactions!$C$3:$C$80, "BUY") | F5: =IF(E5>0, G5/E5, 0) | G5: =SUMIFS(Transactions!$H$3:$H$80, Transactions!$D$3:$D$80, A5, Transactions!$C$3:$C$80, "BUY") | H5: 77.15 | I5: =ROUND(E5*H5, 2) | J5: =I5-G5 | K5: =IF(G5>0, (J5/G5)*100, 0) | L5: =IF(G5>0, (M5/G5)*100, 0) | M5: 0
A6: 0003.HK | B6: Hong Kong and China Gas Co Ltd | C6: Utilities | D6: HKD | E6: =SUMIFS(Transactions!$E$3:$E$80, Transactions!$D$3:$D$80, A6, Transactions!$C$3:$C$80, "BUY") | F6: =IF(E6>0, G6/E6, 0) | G6: =SUMIFS(Transactions!$H$3:$H$80, Transactions!$D$3:$D$80, A6, Transactions!$C$3:$C$80, "BUY") | H6: 7.215 | I6: =ROUND(E6*H6, 2) | J6: =I6-G6 | K6: =IF(G6>0, (J6/G6)*100, 0) | L6: =IF(G6>0, (M6/G6)*100, 0) | M6: 0
A7: 1288.HK | B7: Agricultural Bank of China Ltd | C7: Financials | D7: HKD | E7: =SUMIFS(Transactions!$E$3:$E$80, Transactions!$D$3:$D$80, A7, Transactions!$C$3:$C$80, "BUY") | F7: =IF(E7>0, G7/E7, 0) | G7: =SUMIFS(Transactions!$H$3:$H$80, Transactions!$D$3:$D$80, A7, Transactions!$C$3:$C$80, "BUY") | H7: 6.74 | I7: =ROUND(E7*H7, 2) | J7: =I7-G7 | K7: =IF(G7>0, (J7/G7)*100, 0) | L7: =IF(G7>0, (M7/G7)*100, 0) | M7: 0
A8: 1093.HK | B8: CSPC Pharmaceutical Group Ltd | C8: Healthcare | D8: HKD | E8: =SUMIFS(Transactions!$E$3:$E$80, Transactions!$D$3:$D$80, A8, Transactions!$C$3:$C$80, "BUY") | F8: =IF(E8>0, G8/E8, 0) | G8: =SUMIFS(Transactions!$H$3:$H$80, Transactions!$D$3:$D$80, A8, Transactions!$C$3:$C$80, "BUY") | H8: 8.88 | I8: =ROUND(E8*H8, 2) | J8: =I8-G8 | K8: =IF(G8>0, (J8/G8)*100, 0) | L8: =IF(G8>0, (M8/G8)*100, 0) | M8: 0
A9: 0939.HK | B9: China Construction Bank Corp | C9: Financials | D9: HKD | E9: =SUMIFS(Transactions!$E$3:$E$80, Transactions!$D$3:$D$80, A9, Transactions!$C$3:$C$80, "BUY") | F9: =IF(E9>0, G9/E9, 0) | G9: =SUMIFS(Transactions!$H$3:$H$80, Transactions!$D$3:$D$80, A9, Transactions!$C$3:$C$80, "BUY") | H9: 9.865 | I9: =ROUND(E9*H9, 2) | J9: =I9-G9 | K9: =IF(G9>0, (J9/G9)*100, 0) | L9: =IF(G9>0, (M9/G9)*100, 0) | M9: 0
A10: 0012.HK | B10: Henderson Land Development Co Ltd | C10: Real Estate | D10: HKD | E10: =SUMIFS(Transactions!$E$3:$E$80, Transactions!$D$3:$D$80, A10, Transactions!$C$3:$C$80, "BUY") | F10: =IF(E10>0, G10/E10, 0) | G10: =SUMIFS(Transactions!$H$3:$H$80, Transactions!$D$3:$D$80, A10, Transactions!$C$3:$C$80, "BUY") | H10: 27.2 | I10: =ROUND(E10*H10, 2) | J10: =I10-G10 | K10: =IF(G10>0, (J10/G10)*100, 0) | L10: =IF(G10>0, (M10/G10)*100, 0) | M10: 0
A11: 0066.HK | B11: MTR Corporation Ltd | C11: Industrials | D11: HKD | E11: =SUMIFS(Transactions!$E$3:$E$80, Transactions!$D$3:$D$80, A11, Transactions!$C$3:$C$80, "BUY") | F11: =IF(E11>0, G11/E11, 0) | G11: =SUMIFS(Transactions!$H$3:$H$80, Transactions!$D$3:$D$80, A11, Transactions!$C$3:$C$80, "BUY") | H11: 32.38 | I11: =ROUND(E11*H11, 2) | J11: =I11-G11 | K11: =IF(G11>0, (J11/G11)*100, 0) | L11: =IF(G11>0, (M11/G11)*100, 0) | M11: 0
A12: 0101.HK | B12: Hang Lung Properties Ltd | C12: Real Estate | D12: HKD | E12: =SUMIFS(Transactions!$E$3:$E$80, Transactions!$D$3:$D$80, A12, Transactions!$C$3:$C$80, "BUY") | F12: =IF(E12>0, G12/E12, 0) | G12: =SUMIFS(Transactions!$H$3:$H$80, Transactions!$D$3:$D$80, A12, Transactions!$C$3:$C$80, "BUY") | H12: 6.4 | I12: =ROUND(E12*H12, 2) | J12: =I12-G12 | K12: =IF(G12>0, (J12/G12)*100, 0) | L12: =IF(G12>0, (M12/G12)*100, 0) | M12: 0
A13: 1398.HK | B13: Industrial and Commercial Bank of China Ltd | C13: Financials | D13: HKD | E13: =SUMIFS(Transactions!$E$3:$E$80, Transactions!$D$3:$D$80, A13, Transactions!$C$3:$C$80, "BUY") | F13: =IF(E13>0, G13/E13, 0) | G13: =SUMIFS(Transactions!$H$3:$H$80, Transactions!$D$3:$D$80, A13, Transactions!$C$3:$C$80, "BUY") | H13: 7.59 | I13: =ROUND(E13*H13, 2) | J13: =I13-G13 | K13: =IF(G13>0, (J13/G13)*100, 0) | L13: =IF(G13>0, (M13/G13)*100, 0) | M13: 0
... A23: 2840.HK | B23: SPDR Gold Trust | C23: Index ETF | D23: HKD | E23: =SUMIFS(Transactions!$E$3:$E$80, Transactions!$D$3:$D$80, A23, Transactions!$C$3:$C$80, "BUY") | F23: =IF(E23>0, G23/E23, 0) | G23: =SUMIFS(Transactions!$H$3:$H$80, Transactions!$D$3:$D$80, A23, Transactions!$C$3:$C$80, "BUY") | H23: 3011 | I23: =ROUND(E23*H23, 2) | J23: =I23-G23 | K23: =IF(G23>0, (J23/G23)*100, 0) | L23: =IF(G23>0, (M23/G23)*100, 0) | M23: 0
B24: TOTAL ACTIVE HOLDINGS (22 POSITIONS) | D24: HKD | E24: =SUM(E2:E23) | F24: =IF(E24>0, G24/E24, 0) | G24: =SUM(G2:G23) | H24: 0 | I24: =SUM(I2:I23) | J24: =SUM(J2:J23) | K24: =IF(G24>0, (J24/G24)*100, 0) | L24: =IF(G24>0, (M24/G24)*100, 0) | M24: =SUM(M2:M23)

Sheet Transactions
A1: Transaction ID | B1: Date | C1: Type | D1: Ticker | E1: Shares | F1: Price per Share ($) | G1: Fees ($) | H1: Net Total ($) | I1: Realized Gain/Loss ($) | J1: Notes
A2: TX-DEP-001 | B2: 2018-11-01 | C2: DEPOSIT | D2: CASH | E2: 0 | F2: 0 | G2: 0 | H2: =SUM(H3:H80) | I2: 0 | J2: Auto-funded capital deposit matching total cost basis of 78 imported Yahoo Finance lots
A3: TX-YF-001 | B3: 2018-11-26 | C3: BUY | D3: 2800.HK | E3: 500 | F3: 26.56 | G3: 0 | H3: =ROUND(E3*F3+G3, 2) | I3: 0 | J3: Yahoo Finance: KC ETF - HSI (2800.HK - Lot 13 at bottom edge; date estimated Nov 2018)
A4: TX-YF-002 | B4: 2018-12-24 | C4: BUY | D4: 2800.HK | E4: 500 | F4: 25.81 | G4: 0 | H4: =ROUND(E4*F4+G4, 2) | I4: 0 | J4: Yahoo Finance: KC ETF - HSI (2800.HK - 24 Dec 2018)
A5: TX-YF-003 | B5: 2019-01-25 | C5: BUY | D5: 2800.HK | E5: 500 | F5: 27.76 | G5: 0 | H5: =ROUND(E5*F5+G5, 2) | I5: 0 | J5: Yahoo Finance: KC ETF - HSI (2800.HK - 25 Jan 2019)
A6: TX-YF-004 | B6: 2019-02-25 | C6: BUY | D6: 2800.HK | E6: 500 | F6: 29.41 | G6: 0 | H6: =ROUND(E6*F6+G6, 2) | I6: 0 | J6: Yahoo Finance: KC ETF - HSI (2800.HK - 25 Feb 2019)
A7: TX-YF-005 | B7: 2019-03-25 | C7: BUY | D7: 2800.HK | E7: 500 | F7: 29.01 | G7: 0 | H7: =ROUND(E7*F7+G7, 2) | I7: 0 | J7: Yahoo Finance: KC ETF - HSI (2800.HK - 25 Mar 2019)
A8: TX-YF-006 | B8: 2019-04-29 | C8: BUY | D8: 2800.HK | E8: 500 | F8: 30.06 | G8: 0 | H8: =ROUND(E8*F8+G8, 2) | I8: 0 | J8: Yahoo Finance: KC ETF - HSI (2800.HK - 29 Apr 2019)
A9: TX-YF-007 | B9: 2019-05-27 | C9: BUY | D9: 2800.HK | E9: 500 | F9: 27.76 | G9: 0 | H9: =ROUND(E9*F9+G9, 2) | I9: 0 | J9: Yahoo Finance: KC ETF - HSI (2800.HK - 27 May 2019)
A10: TX-YF-008 | B10: 2019-06-24 | C10: BUY | D10: 2800.HK | E10: 500 | F10: 29.16 | G10: 0 | H10: =ROUND(E10*F10+G10, 2) | I10: 0 | J10: Yahoo Finance: KC ETF - HSI (2800.HK - 24 Jun 2019)
A11: TX-YF-009 | B11: 2019-07-22 | C11: BUY | D11: 2800.HK | E11: 500 | F11: 29.16 | G11: 0 | H11: =ROUND(E11*F11+G11, 2) | I11: 0 | J11: Yahoo Finance: KC ETF - HSI (2800.HK - 22 Jul 2019)
A12: TX-YF-010 | B12: 2019-09-24 | C12: BUY | D12: 2800.HK | E12: 500 | F12: 27.26 | G12: 0 | H12: =ROUND(E12*F12+G12, 2) | I12: 0 | J12: Yahoo Finance: KC ETF - HSI (2800.HK - 24 Sept 2019)
A13: TX-YF-011 | B13: 2019-10-28 | C13: BUY | D13: 2800.HK | E13: 500 | F13: 27.91 | G13: 0 | H13: =ROUND(E13*F13+G13, 2) | I13: 0 | J13: Yahoo Finance: KC ETF - HSI (2800.HK - 28 Oct 2019)
A14: TX-YF-012 | B14: 2019-11-27 | C14: BUY | D14: 2800.HK | E14: 500 | F14: 27.26 | G14: 0 | H14: =ROUND(E14*F14+G14, 2) | I14: 0 | J14: Yahoo Finance: KC ETF - HSI (2800.HK - 27 Nov 2019)
... A80: TX-YF-078 | B80: 2026-09-18 | C80: BUY | D80: 3077.HK | E80: 10 | F80: 3973.72 | G80: 0 | H80: =ROUND(E80*F80+G80, 2) | I80: 0 | J80: Yahoo Finance: KC ETF (3077.HK - 18 Sept 2026, Lot 1 of 2)

Sheet Dividends
A1: Dividend ID | B1: Ticker | C1: Pay Date | D1: Ex Date | E1: Payout Per Share ($) | F1: Total Payout ($) | G1: DRIP Reinvested | H1: DRIP Shares Added | I1: Notes

Sheet Watchlist_Fundamentals
A1: Ticker | B1: Company Name | C1: Sector | D1: Current Price ($) | E1: Target Buy Price ($) | F1: On Watchlist | G1: P/E Ratio | H1: Forward P/E | I1: EPS ($) | J1: Book Value/Share ($) | K1: Market Cap | L1: Debt to Equity | M1: ROE (%) | N1: Free Cash Flow | O1: FCF Per Share ($) | P1: Div Yield (%)
A2: 2318.HK | B2: Ping An Insurance (Group) Co of China Ltd | C2: Financials | D2: 50.05 | E2: 45 | F2: YES | G2: 8.4 | H2: 7.9 | I2: 5.96 | J2: 54.2 | K2: 915.00B | L2: 0.85 | M2: 13.8 | N2: 142.0B | O2: 5.2 | P2: 4.95
A3: 0857.HK | B3: PetroChina Co Ltd | C3: Energy | D3: 9.995 | E3: 8.5 | F3: YES | G3: 9.5 | H3: 9.1 | I3: 1.05 | J3: 8.9 | K3: 1.83T | L3: 0.24 | M3: 11.8 | N3: 210.0B | O3: 1.15 | P3: 5.2
A4: 0386.HK | B4: China Petroleum & Chemical Corp (Sinopec) | C4: Energy | D4: 4.5 | E4: 4.1 | F4: YES | G4: 8.9 | H4: 8.4 | I4: 0.51 | J4: 6.85 | K4: 545.00B | L4: 0.35 | M4: 8.6 | N4: 95.0B | O4: 0.55 | P4: 6.8
A5: 0002.HK | B5: CLP Holdings Ltd | C5: Utilities | D5: 77.15 | E5: 66 | F5: YES | G5: 14.8 | H5: 14.2 | I5: 5.21 | J5: 42.5 | K5: 195.00B | L5: 0.48 | M5: 11.4 | N5: 14.5B | O5: 4.8 | P5: 4.02
A6: 0003.HK | B6: Hong Kong and China Gas Co Ltd | C6: Utilities | D6: 7.215 | E6: 6.75 | F6: YES | G6: 21.2 | H6: 19.8 | I6: 0.34 | J6: 3.25 | K6: 134.60B | L6: 0.72 | M6: 10.2 | N6: 6.8B | O6: 0.31 | P6: 4.85
A7: 1288.HK | B7: Agricultural Bank of China Ltd | C7: Financials | D7: 6.74 | E7: 5.5 | F7: YES | G7: 6.4 | H7: 6.1 | I7: 1.05 | J7: 7.8 | K7: 2.35T | L7: 0 | M7: 10.8 | N7: - | O7: 0.95 | P7: 5.1
A8: 1093.HK | B8: CSPC Pharmaceutical Group Ltd | C8: Healthcare | D8: 8.88 | E8: 7.6 | F8: YES | G8: 14.5 | H8: 13.6 | I8: 0.61 | J8: 3.1 | K8: 105.80B | L8: 0.05 | M8: 17.5 | N8: 7.2B | O8: 0.58 | P8: 3.1
A9: 0939.HK | B9: China Construction Bank Corp | C9: Financials | D9: 9.865 | E9: 7.75 | F9: YES | G9: 6.2 | H9: 5.95 | I9: 1.59 | J9: 12.8 | K9: 2.46T | L9: 0 | M9: 11.5 | N9: - | O9: 1.4 | P9: 5.4
A10: 0012.HK | B10: Henderson Land Development Co Ltd | C10: Real Estate | D10: 27.2 | E10: 26 | F10: YES | G10: 13.6 | H10: 13.1 | I10: 2 | J10: 66.8 | K10: 131.70B | L10: 0.42 | M10: 3.2 | N10: 9.4B | O10: 1.85 | P10: 6.62
A11: 0066.HK | B11: MTR Corporation Ltd | C11: Industrials | D11: 32.38 | E11: 31 | F11: YES | G11: 16.8 | H11: 15.5 | I11: 1.93 | J11: 29.1 | K11: 201.20B | L11: 0.31 | M11: 6.8 | N11: 11.2B | O11: 1.75 | P11: 4.05
A12: 0101.HK | B12: Hang Lung Properties Ltd | C12: Real Estate | D12: 6.4 | E12: 6.2 | F12: YES | G12: 7.4 | H12: 7.1 | I12: 0.86 | J12: 28.4 | K12: 30.20B | L12: 0.36 | M12: 3.1 | N12: 3.8B | O12: 0.78 | P12: 8.12
A13: 1398.HK | B13: Industrial and Commercial Bank of China Ltd | C13: Financials | D13: 7.59 | E13: 6 | F13: YES | G13: 6.3 | H13: 6 | I13: 1.2 | J13: 10.4 | K13: 2.70T | L13: 0 | M13: 10.6 | N13: - | O13: 1.08 | P13: 5.25
... A23: 2840.HK | B23: SPDR Gold Trust | C23: Index ETF | D23: 3011 | E23: 2900 | F23: YES | G23: 0 | H23: 0 | I23: 0 | J23: 3011 | K23: 580.00B | L23: 0 | M23: 0 | N23: - | O23: 0 | P23: 0

Sheet Historical_Prices
A1: Ticker | B1: Month | C1: Close Price ($) | D1: High ($) | E1: Low ($) | F1: Volume
